stmp/__init__.py
stmp/exceptions.py
stmp/interfaces.py
stmp/server.py
stmp/settings.py
stmp/stmp_server/__init__.py
stmp/stmp_server/stmp_server.py
stmp/stmp_server/transilation/__init__.py
stmp/stmp_server/transilation/transilation.py
stmp/stmp_server/transilation/enc/__init__.py
stmp/stmp_server/transilation/enc/crypt.py
stmp/stmp_server/transport/__init__.py
stmp/stmp_server/transport/interfaces.py
stmp/stmp_server/transport/transport.py
stmp_server-0.0.3.dist-info/LICENSE
stmp_server-0.0.3.dist-info/METADATA
stmp_server-0.0.3.dist-info/WHEEL
stmp_server-0.0.3.dist-info/top_level.txt
stmp_server-0.0.3.dist-info/RECORD
