Metadata-Version: 2.1
Name: stmp-server
Version: 0.0.3
Summary: A primitive zero-configuration local network protocol purely written in python, originally intended for tinkering with your office mates over LAN!
Author-email: "@bRuttaZz" <agrajpdasprivate@gmail.com>
License: MIT License
Project-URL: Homepage, https://github.com/bRuttaZz/stmp
Project-URL: Issues, https://github.com/bRuttaZz/stmp/issues
Project-URL: Repository, https://github.com/bRuttaZz/stmp.git
Project-URL: Documentation, https://pypi.org/project/stmp-server/
Keywords: stmp,sitty-talky,sittytalky,LAN,WLAN,peer-discovery,Messaging,protocol,multicast dns,dns,udp,tcp
Classifier: Development Status :: 4 - Beta
Classifier: Intended Audience :: Developers
Classifier: Intended Audience :: Science/Research
Classifier: License :: OSI Approved :: MIT License
Classifier: Operating System :: POSIX
Classifier: Operating System :: POSIX :: Linux
Classifier: Operating System :: Unix
Classifier: Programming Language :: Python :: 3.11
Classifier: Programming Language :: Python :: 3.12
Classifier: Programming Language :: Python :: 3.13
Classifier: Topic :: Communications :: Chat
Classifier: Topic :: Internet
Classifier: Topic :: Software Development
Classifier: Natural Language :: English
Requires-Python: >=3.11
License-File: LICENSE
Requires-Dist: pycryptodome ==3.20.0
